{
    "storage_charge_controller_in": {
        "age_installed": "{'value': 0.0, 'unit': 'year'}",
        "capex_fix": "{'value': 0.0, 'unit': 'currency'}",
        "capex_var": "{'value': 0.0, 'unit': 'currency/kW'}",
        "efficiency": "{'value': 1, 'unit': 'factor'}",
        "inflow_direction": "Electricity (LES)",
        "installedCap": "{'value': 0.0, 'unit': 'kW'}",
        "label": "Charge Contoller ESS Li-Ion (charge)",
        "lifetime": "{'value': 10, 'unit': 'year'}",
        "opex_fix": "{'value': 0.0, 'unit': 'currency/kW/year'}",
        "opex_var": "{'value': 0.0, 'unit': 'currency/kWh'}",
        "optimizeCap": "True",
        "outflow_direction": "ESS Li-Ion",
        "type_oemof": "transformer"
    },
    "storage_charge_controller_out": {
        "age_installed": "{'value': 0.0, 'unit': 'year'}",
        "capex_fix": "{'value': 0.0, 'unit': 'currency'}",
        "capex_var": "{'value': 0.0, 'unit': 'currency/kW'}",
        "efficiency": "{'value': 1, 'unit': 'factor'}",
        "inflow_direction": "ESS Li-Ion",
        "installedCap": "{'value': 0.0, 'unit': 'kW'}",
        "label": "Charge Contoller ESS Li-Ion (discharge)",
        "lifetime": "{'value': 10, 'unit': 'year'}",
        "opex_fix": "{'value': 0.0, 'unit': 'currency/kW/year'}",
        "opex_var": "{'value': 0.0, 'unit': 'currency/kWh'}",
        "optimizeCap": "True",
        "outflow_direction": "Electricity (LES)",
        "type_oemof": "transformer"
    },
    "solar_inverter_01": {
        "age_installed": "{'value': 0, 'unit': 'year'}",
        "capex_fix": "{'value': 0.0, 'unit': 'currency'}",
        "capex_var": "{'value': 3000, 'unit': 'currency/kW'}",
        "efficiency": "{'value': 1.0, 'unit': 'factor'}",
        "inflow_direction": "PV plant (mono)",
        "installedCap": "{'value': 0, 'unit': 'kW'}",
        "label": "Solar inverter (mono)",
        "lifetime": "{'value': 15, 'unit': 'year'}",
        "opex_fix": "{'value': 0, 'unit': 'currency/kW/year'}",
        "opex_var": "{'value': 0, 'unit': 'currency/kWh'}",
        "optimizeCap": "True",
        "outflow_direction": "Electricity (LES)",
        "type_oemof": "transformer"
    },
    "transformer_station_in": {
        "age_installed": "{'value': 5, 'unit': 'year'}",
        "capex_fix": "{'value': 0.0, 'unit': 'currency'}",
        "capex_var": "{'value': 0, 'unit': 'currency/kW'}",
        "efficiency": "{'value': 0.96, 'unit': 'factor'}",
        "inflow_direction": "Electricity (DSO)",
        "installedCap": "{'value': 1250, 'unit': 'kW'}",
        "label": "Transformer station (DSO) consumption",
        "lifetime": "{'value': 30, 'unit': 'year'}",
        "opex_fix": "{'value': 0, 'unit': 'currency/kW/year'}",
        "opex_var": "{'value': 0, 'unit': 'currency/kWh'}",
        "optimizeCap": "False",
        "outflow_direction": "Electricity (LES)",
        "type_oemof": "transformer"
    },
    "transformer_station_out": {
        "age_installed": "{'value': 5, 'unit': 'year'}",
        "capex_fix": "{'value': 0.0, 'unit': 'currency'}",
        "capex_var": "{'value': 0, 'unit': 'currency/kW'}",
        "efficiency": "{'value': 0.96, 'unit': 'factor'}",
        "inflow_direction": "Electricity (LES)",
        "installedCap": "{'value': 1250, 'unit': 'kW'}",
        "label": "Transformer station (DSO) feedin",
        "lifetime": "{'value': 30, 'unit': 'year'}",
        "opex_fix": "{'value': 0, 'unit': 'currency/kW/year'}",
        "opex_var": "{'value': 0, 'unit': 'currency/kWh'}",
        "optimizeCap": "False",
        "outflow_direction": "Electricity (DSO)",
        "type_oemof": "transformer"
    },
    "diesel_generator": {
        "age_installed": "{'value': 0, 'unit': 'year'}",
        "capex_fix": "{'value': 0, 'unit': 'currency'}",
        "capex_var": "{'value': 600, 'unit': 'currency/kW'}",
        "efficiency": "{'value': 0.33, 'unit': 'factor'}",
        "inflow_direction": "Fuel",
        "installedCap": "{'value': 0, 'unit': 'kW'}",
        "label": "Backup diesel generator",
        "lifetime": "{'value': 15, 'unit': 'year'}",
        "opex_fix": "{'value': 5, 'unit': 'currency/kW/year'}",
        "opex_var": "{'value': 0, 'unit': 'currency/kWh'}",
        "optimizeCap": "True",
        "outflow_direction": "Electricity (LES)",
        "type_oemof": "transformer"
    }
}